README.md
setup.py
thefilewatch/__init__.py
thefilewatch/file_watch.py
thefilewatch.egg-info/PKG-INFO
thefilewatch.egg-info/SOURCES.txt
thefilewatch.egg-info/dependency_links.txt
thefilewatch.egg-info/requires.txt
thefilewatch.egg-info/top_level.txt