Metadata-Version: 2.1
Name: thefilewatch
Version: 0.0.8
Summary: multi-files watcher
Home-page: https://github.com/johnlofty/thefilewatch
Author: johnlofty
Author-email: johnlofty@163.com
License: UNKNOWN
Platform: UNKNOWN
